pip_pin/__init__.py
pip_pin/commands.py
pip_pin/egg_info.py
pip_pin-0.0.10.dist-info/METADATA
pip_pin-0.0.10.dist-info/WHEEL
pip_pin-0.0.10.dist-info/develop_requires.txt
pip_pin-0.0.10.dist-info/entry_points.txt
pip_pin-0.0.10.dist-info/tests_require.txt
pip_pin-0.0.10.dist-info/top_level.txt
pip_pin-0.0.10.dist-info/RECORD
