Metadata-Version: 2.1
Name: pip-pin
Version: 0.0.10
Summary: Pippin
Home-page: https://github.com/mrzechonek/python-pip-pin
Author: Michał Lowas-Rzechonek
Author-email: michal@rzechonek.net
License: MIT
Platform: UNKNOWN
Classifier: Development Status :: 3 - Alpha
Classifier: Intended Audience :: Developers
Classifier: License :: OSI Approved :: MIT License
Classifier: Programming Language :: Python :: 3.6
Classifier: Programming Language :: Python :: 3.7
Classifier: Programming Language :: Python :: 3.8
Classifier: Topic :: Software Development :: Testing
Requires-Python: >= 3.6
